Haversine
