Metadata-Version: 2.1
Name: HaversineAPI
Version: 1.18
Summary: UNKNOWN
Home-page: https://github.com/eddo888/HaversineAPI
Author: David Edson
Author-email: eddo888@tpg.com.au
License: MIT
Download-URL: https://github.com/eddo888/HaversineAPI/archive/1.18.tar.gz
Platform: UNKNOWN
